fastapi_dbbackup/__init__.py
fastapi_dbbackup/__version__.py
fastapi_dbbackup/base.py
fastapi_dbbackup/cli.py
fastapi_dbbackup/compress.py
fastapi_dbbackup/config.py
fastapi_dbbackup/detector.py
fastapi_dbbackup/exceptions.py
fastapi_dbbackup/retention.py
fastapi_dbbackup/engines/__init__.py
fastapi_dbbackup/engines/mysql.py
fastapi_dbbackup/engines/postgres.py
fastapi_dbbackup/engines/sqlite.py
fastapi_dbbackup/storage/__init__.py
fastapi_dbbackup/storage/base.py
fastapi_dbbackup/storage/local.py
fastapi_dbbackup/storage/s3.py
fastapi_dbbackup-0.1.3.dist-info/licenses/LICENSE
fastapi_dbbackup-0.1.3.dist-info/METADATA
fastapi_dbbackup-0.1.3.dist-info/WHEEL
fastapi_dbbackup-0.1.3.dist-info/entry_points.txt
fastapi_dbbackup-0.1.3.dist-info/top_level.txt
fastapi_dbbackup-0.1.3.dist-info/RECORD
