Metadata-Version: 2.4
Name: fastapi-dbbackup
Version: 0.1.3
Summary: Database-native backup tool for FastAPI, SQLAlchemy, and SQLModel projects.
Author-email: Rajesh <contact@geekyshows.com>
License-Expression: MIT
Project-URL: Homepage, https://github.com/rajsolodev/fastapi-dbbackup
Project-URL: Repository, https://github.com/rajsolodev/fastapi-dbbackup
Project-URL: Bug Tracker, https://github.com/rajsolodev/fastapi-dbbackup/issues
Keywords: fastapi,sqlalchemy,sqlmodel,backup,database,postgres,mysql,sqlite,s3
Classifier: Development Status :: 4 - Beta
Classifier: Intended Audience :: Developers
Classifier: Topic :: Database
Classifier: Topic :: System :: Archiving :: Backup
Classifier: Programming Language :: Python :: 3
Classifier: Programming Language :: Python :: 3.8
Classifier: Programming Language :: Python :: 3.9
Classifier: Programming Language :: Python :: 3.10
Classifier: Programming Language :: Python :: 3.11
Classifier: Programming Language :: Python :: 3.12
Classifier: Programming Language :: Python :: 3.13
Classifier: Programming Language :: Python :: 3.14
Requires-Python: >=3.8
License-File: LICENSE
Requires-Dist: sqlalchemy>=2.0.0
Requires-Dist: boto3>=1.26.0
Requires-Dist: python-dotenv>=1.0.0
Provides-Extra: dev
Requires-Dist: pytest>=7.0.0; extra == "dev"
Requires-Dist: pytest-cov; extra == "dev"
Requires-Dist: black; extra == "dev"
Requires-Dist: isort; extra == "dev"
Requires-Dist: mypy; extra == "dev"
Dynamic: license-file
